Metadata-Version: 2.1
Name: odoo13-addon-project-duplicate-subtask
Version: 13.0.1.0.2
Summary: The module adds an action to duplicate tasks with the child subtasks
Home-page: https://github.com/OCA/project
Author: Forgeflow, Odoo Community Association (OCA)
Author-email: support@odoo-community.org
License: AGPL-3
Platform: UNKNOWN
Classifier: Programming Language :: Python
Classifier: Framework :: Odoo
Classifier: License :: OSI Approved :: GNU Affero General Public License v3
Requires-Python: >=3.5
Requires-Dist: odoo (<13.1dev,>=13.0a)
